LICENSE
README.md
setup.py
fedtree/__init__.py
fedtree/fedtree.py
fedtree/libFedTree.so
fedtree.egg-info/PKG-INFO
fedtree.egg-info/SOURCES.txt
fedtree.egg-info/dependency_links.txt
fedtree.egg-info/requires.txt
fedtree.egg-info/top_level.txt