Metadata-Version: 2.1
Name: fedtree
Version: 1.0.4
Summary: A federated learning library for trees
Home-page: https://github.com/Xtra-Computing/FedTree
Author: Qinbin Li
Author-email: liqinbin1998@gmail.com
License: Apache-2.0
Platform: UNKNOWN
Classifier: Programming Language :: Python :: 3
Classifier: License :: OSI Approved :: Apache Software License
License-File: LICENSE
